jobcurator/__init__.py
jobcurator/cuckoo_filter.py
jobcurator/curator.py
jobcurator/faiss_backends.py
jobcurator/hash_utils.py
jobcurator/minhash_backends.py
jobcurator/models.py
jobcurator/sklearn_backends.py
jobcurator/storage/__init__.py
jobcurator/storage/base.py
jobcurator/storage/local_store.py
jobcurator/storage/sql_store.py
jobcurator-1.2.4.dist-info/licenses/LICENSE
jobcurator-1.2.4.dist-info/METADATA
jobcurator-1.2.4.dist-info/WHEEL
jobcurator-1.2.4.dist-info/top_level.txt
jobcurator-1.2.4.dist-info/RECORD
