Metadata-Version: 2.4
Name: jobcurator
Version: 1.2.4
Summary: Open-source Machine Learning Library for Job Data
Author-email: Mouhidine SEIV <mouhidine.seiv@hrflow.ai>
License: MIT License
Project-URL: Homepage, https://github.com/Riminder/jobcurator
Project-URL: Repository, https://github.com/Riminder/jobcurator
Project-URL: Issues, https://github.com/Riminder/jobcurator/issues
Classifier: Programming Language :: Python :: 3
Classifier: Programming Language :: Python :: 3.8
Classifier: Programming Language :: Python :: 3.9
Classifier: Programming Language :: Python :: 3.10
Classifier: License :: OSI Approved :: MIT License
Classifier: Intended Audience :: Developers
Classifier: Topic :: Software Development :: Libraries
Requires-Python: >=3.8
License-File: LICENSE
Dynamic: license-file
